[
  {
    "description": "",
    "elements": [
      {
        "description": "",
        "id": "wikipedia-article-search;search-for-an-article-and-verify-title-and-language-dropdown",
        "keyword": "Scenario Outline",
        "line": 11,
        "name": "Search for an article and verify title and language dropdown",
        "steps": [
          {
            "keyword": "Before",
            "hidden": true,
            "result": {
              "status": "passed",
              "duration": 17459600
            }
          },
          {
            "keyword": "Before",
            "hidden": true,
            "result": {
              "status": "passed",
              "duration": 159712800
            }
          },
          {
            "arguments": [],
            "keyword": "Given ",
            "line": 4,
            "name": "I am on the Wikipedia homepage",
            "match": {
              "location": "file:\\F:\\gitfiles\\githowto\\homework20-KyryloAleksandrov\\src\\steps\\common.steps.ts:11"
            },
            "result": {
              "status": "passed",
              "duration": 437339899
            }
          },
          {
            "arguments": [],
            "keyword": "When ",
            "line": 5,
            "name": "I search for \"Alan Turing\"",
            "match": {
              "location": "file:\\F:\\gitfiles\\githowto\\homework20-KyryloAleksandrov\\src\\steps\\wikipedia-article.steps.ts:12"
            },
            "result": {
              "status": "passed",
              "duration": 831817000
            }
          },
          {
            "arguments": [],
            "keyword": "Then ",
            "line": 6,
            "name": "the article title should be \"Alan Turing\"",
            "match": {
              "location": "file:\\F:\\gitfiles\\githowto\\homework20-KyryloAleksandrov\\src\\steps\\wikipedia-article.steps.ts:17"
            },
            "result": {
              "status": "passed",
              "duration": 354835200
            }
          },
          {
            "arguments": [],
            "keyword": "And ",
            "line": 7,
            "name": "the language dropdown should be visible",
            "match": {
              "location": "file:\\F:\\gitfiles\\githowto\\homework20-KyryloAleksandrov\\src\\steps\\wikipedia-article.steps.ts:23"
            },
            "result": {
              "status": "passed",
              "duration": 83274599
            }
          },
          {
            "keyword": "After",
            "hidden": true,
            "result": {
              "status": "passed",
              "duration": 24232300
            }
          },
          {
            "keyword": "After",
            "hidden": true,
            "result": {
              "status": "passed",
              "duration": 115926699
            }
          }
        ],
        "tags": [],
        "type": "scenario"
      },
      {
        "description": "",
        "id": "wikipedia-article-search;search-for-an-article-and-verify-title-and-language-dropdown",
        "keyword": "Scenario Outline",
        "line": 12,
        "name": "Search for an article and verify title and language dropdown",
        "steps": [
          {
            "keyword": "Before",
            "hidden": true,
            "result": {
              "status": "passed",
              "duration": 5701600
            }
          },
          {
            "keyword": "Before",
            "hidden": true,
            "result": {
              "status": "passed",
              "duration": 103866299
            }
          },
          {
            "arguments": [],
            "keyword": "Given ",
            "line": 4,
            "name": "I am on the Wikipedia homepage",
            "match": {
              "location": "file:\\F:\\gitfiles\\githowto\\homework20-KyryloAleksandrov\\src\\steps\\common.steps.ts:11"
            },
            "result": {
              "status": "passed",
              "duration": 427890599
            }
          },
          {
            "arguments": [],
            "keyword": "When ",
            "line": 5,
            "name": "I search for \"Marie Curie\"",
            "match": {
              "location": "file:\\F:\\gitfiles\\githowto\\homework20-KyryloAleksandrov\\src\\steps\\wikipedia-article.steps.ts:12"
            },
            "result": {
              "status": "passed",
              "duration": 745776399
            }
          },
          {
            "arguments": [],
            "keyword": "Then ",
            "line": 6,
            "name": "the article title should be \"Marie Curie\"",
            "match": {
              "location": "file:\\F:\\gitfiles\\githowto\\homework20-KyryloAleksandrov\\src\\steps\\wikipedia-article.steps.ts:17"
            },
            "result": {
              "status": "passed",
              "duration": 362465799
            }
          },
          {
            "arguments": [],
            "keyword": "And ",
            "line": 7,
            "name": "the language dropdown should be visible",
            "match": {
              "location": "file:\\F:\\gitfiles\\githowto\\homework20-KyryloAleksandrov\\src\\steps\\wikipedia-article.steps.ts:23"
            },
            "result": {
              "status": "passed",
              "duration": 74274999
            }
          },
          {
            "keyword": "After",
            "hidden": true,
            "result": {
              "status": "passed",
              "duration": 21275099
            }
          },
          {
            "keyword": "After",
            "hidden": true,
            "result": {
              "status": "passed",
              "duration": 102294799
            }
          }
        ],
        "tags": [],
        "type": "scenario"
      },
      {
        "description": "",
        "id": "wikipedia-article-search;search-for-an-article-and-verify-title-and-language-dropdown",
        "keyword": "Scenario Outline",
        "line": 13,
        "name": "Search for an article and verify title and language dropdown",
        "steps": [
          {
            "keyword": "Before",
            "hidden": true,
            "result": {
              "status": "passed",
              "duration": 6319399
            }
          },
          {
            "keyword": "Before",
            "hidden": true,
            "result": {
              "status": "passed",
              "duration": 100778299
            }
          },
          {
            "arguments": [],
            "keyword": "Given ",
            "line": 4,
            "name": "I am on the Wikipedia homepage",
            "match": {
              "location": "file:\\F:\\gitfiles\\githowto\\homework20-KyryloAleksandrov\\src\\steps\\common.steps.ts:11"
            },
            "result": {
              "status": "passed",
              "duration": 418490399
            }
          },
          {
            "arguments": [],
            "keyword": "When ",
            "line": 5,
            "name": "I search for \"Isaac Newton\"",
            "match": {
              "location": "file:\\F:\\gitfiles\\githowto\\homework20-KyryloAleksandrov\\src\\steps\\wikipedia-article.steps.ts:12"
            },
            "result": {
              "status": "passed",
              "duration": 570958799
            }
          },
          {
            "arguments": [],
            "keyword": "Then ",
            "line": 6,
            "name": "the article title should be \"Isaac Newton\"",
            "match": {
              "location": "file:\\F:\\gitfiles\\githowto\\homework20-KyryloAleksandrov\\src\\steps\\wikipedia-article.steps.ts:17"
            },
            "result": {
              "status": "passed",
              "duration": 317426199
            }
          },
          {
            "arguments": [],
            "keyword": "And ",
            "line": 7,
            "name": "the language dropdown should be visible",
            "match": {
              "location": "file:\\F:\\gitfiles\\githowto\\homework20-KyryloAleksandrov\\src\\steps\\wikipedia-article.steps.ts:23"
            },
            "result": {
              "status": "passed",
              "duration": 95345499
            }
          },
          {
            "keyword": "After",
            "hidden": true,
            "result": {
              "status": "passed",
              "duration": 37310999
            }
          },
          {
            "keyword": "After",
            "hidden": true,
            "result": {
              "status": "passed",
              "duration": 47283800
            }
          }
        ],
        "tags": [],
        "type": "scenario"
      }
    ],
    "id": "wikipedia-article-search",
    "line": 1,
    "keyword": "Feature",
    "name": "Wikipedia article search",
    "tags": [],
    "uri": "features\\wikipedia-article-search.feature"
  },
  {
    "description": "",
    "elements": [
      {
        "description": "",
        "id": "wikipedia-disambiguation-page-validation;confirm-a-term-leads-to-a-disambiguation-page",
        "keyword": "Scenario Outline",
        "line": 11,
        "name": "Confirm a term leads to a disambiguation page",
        "steps": [
          {
            "keyword": "Before",
            "hidden": true,
            "result": {
              "status": "passed",
              "duration": 8396700
            }
          },
          {
            "keyword": "Before",
            "hidden": true,
            "result": {
              "status": "passed",
              "duration": 107709500
            }
          },
          {
            "arguments": [],
            "keyword": "Given ",
            "line": 4,
            "name": "I open the article for \"Mercury (disambiguation)\"",
            "match": {
              "location": "file:\\F:\\gitfiles\\githowto\\homework20-KyryloAleksandrov\\src\\steps\\wikipedia-disambiguation.steps.ts:12"
            },
            "result": {
              "status": "passed",
              "duration": 409770300
            }
          },
          {
            "arguments": [],
            "keyword": "Then ",
            "line": 5,
            "name": "the disambiguation page title should be visible",
            "match": {
              "location": "file:\\F:\\gitfiles\\githowto\\homework20-KyryloAleksandrov\\src\\steps\\wikipedia-disambiguation.steps.ts:18"
            },
            "result": {
              "status": "passed",
              "duration": 93168399
            }
          },
          {
            "arguments": [],
            "keyword": "And ",
            "line": 6,
            "name": "the content should indicate it is a disambiguation page",
            "match": {
              "location": "file:\\F:\\gitfiles\\githowto\\homework20-KyryloAleksandrov\\src\\steps\\wikipedia-disambiguation.steps.ts:23"
            },
            "result": {
              "status": "passed",
              "duration": 43692200
            }
          },
          {
            "arguments": [],
            "keyword": "And ",
            "line": 7,
            "name": "at least one disambiguation link should be present",
            "match": {
              "location": "file:\\F:\\gitfiles\\githowto\\homework20-KyryloAleksandrov\\src\\steps\\wikipedia-disambiguation.steps.ts:29"
            },
            "result": {
              "status": "passed",
              "duration": 18213900
            }
          },
          {
            "keyword": "After",
            "hidden": true,
            "result": {
              "status": "passed",
              "duration": 14556099
            }
          },
          {
            "keyword": "After",
            "hidden": true,
            "result": {
              "status": "passed",
              "duration": 56488699
            }
          }
        ],
        "tags": [],
        "type": "scenario"
      },
      {
        "description": "",
        "id": "wikipedia-disambiguation-page-validation;confirm-a-term-leads-to-a-disambiguation-page",
        "keyword": "Scenario Outline",
        "line": 12,
        "name": "Confirm a term leads to a disambiguation page",
        "steps": [
          {
            "keyword": "Before",
            "hidden": true,
            "result": {
              "status": "passed",
              "duration": 8534900
            }
          },
          {
            "keyword": "Before",
            "hidden": true,
            "result": {
              "status": "passed",
              "duration": 107095999
            }
          },
          {
            "arguments": [],
            "keyword": "Given ",
            "line": 4,
            "name": "I open the article for \"Jaguar (disambiguation)\"",
            "match": {
              "location": "file:\\F:\\gitfiles\\githowto\\homework20-KyryloAleksandrov\\src\\steps\\wikipedia-disambiguation.steps.ts:12"
            },
            "result": {
              "status": "passed",
              "duration": 435240699
            }
          },
          {
            "arguments": [],
            "keyword": "Then ",
            "line": 5,
            "name": "the disambiguation page title should be visible",
            "match": {
              "location": "file:\\F:\\gitfiles\\githowto\\homework20-KyryloAleksandrov\\src\\steps\\wikipedia-disambiguation.steps.ts:18"
            },
            "result": {
              "status": "passed",
              "duration": 83724299
            }
          },
          {
            "arguments": [],
            "keyword": "And ",
            "line": 6,
            "name": "the content should indicate it is a disambiguation page",
            "match": {
              "location": "file:\\F:\\gitfiles\\githowto\\homework20-KyryloAleksandrov\\src\\steps\\wikipedia-disambiguation.steps.ts:23"
            },
            "result": {
              "status": "passed",
              "duration": 13723999
            }
          },
          {
            "arguments": [],
            "keyword": "And ",
            "line": 7,
            "name": "at least one disambiguation link should be present",
            "match": {
              "location": "file:\\F:\\gitfiles\\githowto\\homework20-KyryloAleksandrov\\src\\steps\\wikipedia-disambiguation.steps.ts:29"
            },
            "result": {
              "status": "passed",
              "duration": 16577400
            }
          },
          {
            "keyword": "After",
            "hidden": true,
            "result": {
              "status": "passed",
              "duration": 31857700
            }
          },
          {
            "keyword": "After",
            "hidden": true,
            "result": {
              "status": "passed",
              "duration": 34623300
            }
          }
        ],
        "tags": [],
        "type": "scenario"
      },
      {
        "description": "",
        "id": "wikipedia-disambiguation-page-validation;confirm-a-term-leads-to-a-disambiguation-page",
        "keyword": "Scenario Outline",
        "line": 13,
        "name": "Confirm a term leads to a disambiguation page",
        "steps": [
          {
            "keyword": "Before",
            "hidden": true,
            "result": {
              "status": "passed",
              "duration": 10123499
            }
          },
          {
            "keyword": "Before",
            "hidden": true,
            "result": {
              "status": "passed",
              "duration": 107305399
            }
          },
          {
            "arguments": [],
            "keyword": "Given ",
            "line": 4,
            "name": "I open the article for \"Java (disambiguation)\"",
            "match": {
              "location": "file:\\F:\\gitfiles\\githowto\\homework20-KyryloAleksandrov\\src\\steps\\wikipedia-disambiguation.steps.ts:12"
            },
            "result": {
              "status": "passed",
              "duration": 444812599
            }
          },
          {
            "arguments": [],
            "keyword": "Then ",
            "line": 5,
            "name": "the disambiguation page title should be visible",
            "match": {
              "location": "file:\\F:\\gitfiles\\githowto\\homework20-KyryloAleksandrov\\src\\steps\\wikipedia-disambiguation.steps.ts:18"
            },
            "result": {
              "status": "passed",
              "duration": 86702000
            }
          },
          {
            "arguments": [],
            "keyword": "And ",
            "line": 6,
            "name": "the content should indicate it is a disambiguation page",
            "match": {
              "location": "file:\\F:\\gitfiles\\githowto\\homework20-KyryloAleksandrov\\src\\steps\\wikipedia-disambiguation.steps.ts:23"
            },
            "result": {
              "status": "passed",
              "duration": 12558999
            }
          },
          {
            "arguments": [],
            "keyword": "And ",
            "line": 7,
            "name": "at least one disambiguation link should be present",
            "match": {
              "location": "file:\\F:\\gitfiles\\githowto\\homework20-KyryloAleksandrov\\src\\steps\\wikipedia-disambiguation.steps.ts:29"
            },
            "result": {
              "status": "passed",
              "duration": 13761899
            }
          },
          {
            "keyword": "After",
            "hidden": true,
            "result": {
              "status": "passed",
              "duration": 25382900
            }
          },
          {
            "keyword": "After",
            "hidden": true,
            "result": {
              "status": "passed",
              "duration": 31945900
            }
          }
        ],
        "tags": [],
        "type": "scenario"
      },
      {
        "description": "",
        "id": "wikipedia-disambiguation-page-validation;confirm-a-term-leads-to-a-disambiguation-page",
        "keyword": "Scenario Outline",
        "line": 14,
        "name": "Confirm a term leads to a disambiguation page",
        "steps": [
          {
            "keyword": "Before",
            "hidden": true,
            "result": {
              "status": "passed",
              "duration": 10800999
            }
          },
          {
            "keyword": "Before",
            "hidden": true,
            "result": {
              "status": "passed",
              "duration": 104029300
            }
          },
          {
            "arguments": [],
            "keyword": "Given ",
            "line": 4,
            "name": "I open the article for \"Delta (disambiguation)\"",
            "match": {
              "location": "file:\\F:\\gitfiles\\githowto\\homework20-KyryloAleksandrov\\src\\steps\\wikipedia-disambiguation.steps.ts:12"
            },
            "result": {
              "status": "passed",
              "duration": 475262499
            }
          },
          {
            "arguments": [],
            "keyword": "Then ",
            "line": 5,
            "name": "the disambiguation page title should be visible",
            "match": {
              "location": "file:\\F:\\gitfiles\\githowto\\homework20-KyryloAleksandrov\\src\\steps\\wikipedia-disambiguation.steps.ts:18"
            },
            "result": {
              "status": "passed",
              "duration": 103668899
            }
          },
          {
            "arguments": [],
            "keyword": "And ",
            "line": 6,
            "name": "the content should indicate it is a disambiguation page",
            "match": {
              "location": "file:\\F:\\gitfiles\\githowto\\homework20-KyryloAleksandrov\\src\\steps\\wikipedia-disambiguation.steps.ts:23"
            },
            "result": {
              "status": "passed",
              "duration": 29719300
            }
          },
          {
            "arguments": [],
            "keyword": "And ",
            "line": 7,
            "name": "at least one disambiguation link should be present",
            "match": {
              "location": "file:\\F:\\gitfiles\\githowto\\homework20-KyryloAleksandrov\\src\\steps\\wikipedia-disambiguation.steps.ts:29"
            },
            "result": {
              "status": "passed",
              "duration": 16052200
            }
          },
          {
            "keyword": "After",
            "hidden": true,
            "result": {
              "status": "passed",
              "duration": 10085300
            }
          },
          {
            "keyword": "After",
            "hidden": true,
            "result": {
              "status": "passed",
              "duration": 33858899
            }
          }
        ],
        "tags": [],
        "type": "scenario"
      },
      {
        "description": "",
        "id": "wikipedia-disambiguation-page-validation;confirm-a-term-leads-to-a-disambiguation-page",
        "keyword": "Scenario Outline",
        "line": 15,
        "name": "Confirm a term leads to a disambiguation page",
        "steps": [
          {
            "keyword": "Before",
            "hidden": true,
            "result": {
              "status": "passed",
              "duration": 10010700
            }
          },
          {
            "keyword": "Before",
            "hidden": true,
            "result": {
              "status": "passed",
              "duration": 106607799
            }
          },
          {
            "arguments": [],
            "keyword": "Given ",
            "line": 4,
            "name": "I open the article for \"Saturn (disambiguation)\"",
            "match": {
              "location": "file:\\F:\\gitfiles\\githowto\\homework20-KyryloAleksandrov\\src\\steps\\wikipedia-disambiguation.steps.ts:12"
            },
            "result": {
              "status": "passed",
              "duration": 414709800
            }
          },
          {
            "arguments": [],
            "keyword": "Then ",
            "line": 5,
            "name": "the disambiguation page title should be visible",
            "match": {
              "location": "file:\\F:\\gitfiles\\githowto\\homework20-KyryloAleksandrov\\src\\steps\\wikipedia-disambiguation.steps.ts:18"
            },
            "result": {
              "status": "passed",
              "duration": 71272500
            }
          },
          {
            "arguments": [],
            "keyword": "And ",
            "line": 6,
            "name": "the content should indicate it is a disambiguation page",
            "match": {
              "location": "file:\\F:\\gitfiles\\githowto\\homework20-KyryloAleksandrov\\src\\steps\\wikipedia-disambiguation.steps.ts:23"
            },
            "result": {
              "status": "passed",
              "duration": 17628699
            }
          },
          {
            "arguments": [],
            "keyword": "And ",
            "line": 7,
            "name": "at least one disambiguation link should be present",
            "match": {
              "location": "file:\\F:\\gitfiles\\githowto\\homework20-KyryloAleksandrov\\src\\steps\\wikipedia-disambiguation.steps.ts:29"
            },
            "result": {
              "status": "passed",
              "duration": 17451600
            }
          },
          {
            "keyword": "After",
            "hidden": true,
            "result": {
              "status": "passed",
              "duration": 36883299
            }
          },
          {
            "keyword": "After",
            "hidden": true,
            "result": {
              "status": "passed",
              "duration": 39908899
            }
          }
        ],
        "tags": [],
        "type": "scenario"
      }
    ],
    "id": "wikipedia-disambiguation-page-validation",
    "line": 1,
    "keyword": "Feature",
    "name": "Wikipedia disambiguation page validation",
    "tags": [],
    "uri": "features\\wikipedia-disambiguation.feature"
  },
  {
    "description": "",
    "elements": [
      {
        "description": "",
        "id": "wikipedia-article-language-switch;switch-article-to-another-language",
        "keyword": "Scenario Outline",
        "line": 12,
        "name": "Switch article to another language",
        "steps": [
          {
            "keyword": "Before",
            "hidden": true,
            "result": {
              "status": "passed",
              "duration": 8969999
            }
          },
          {
            "keyword": "Before",
            "hidden": true,
            "result": {
              "status": "passed",
              "duration": 105075499
            }
          },
          {
            "arguments": [],
            "keyword": "Given ",
            "line": 4,
            "name": "I am on the Wikipedia homepage",
            "match": {
              "location": "file:\\F:\\gitfiles\\githowto\\homework20-KyryloAleksandrov\\src\\steps\\common.steps.ts:11"
            },
            "result": {
              "status": "passed",
              "duration": 428996499
            }
          },
          {
            "arguments": [],
            "keyword": "When ",
            "line": 5,
            "name": "I search for \"Alan Turing\"",
            "match": {
              "location": "file:\\F:\\gitfiles\\githowto\\homework20-KyryloAleksandrov\\src\\steps\\wikipedia-article.steps.ts:12"
            },
            "result": {
              "status": "passed",
              "duration": 587599299
            }
          },
          {
            "arguments": [],
            "keyword": "And ",
            "line": 6,
            "name": "I switch the article language to \"es\"",
            "match": {
              "location": "file:\\F:\\gitfiles\\githowto\\homework20-KyryloAleksandrov\\src\\steps\\wikipedia-language.steps.ts:12"
            },
            "result": {
              "status": "passed",
              "duration": 716378400
            }
          },
          {
            "arguments": [],
            "keyword": "Then ",
            "line": 7,
            "name": "I should be on the \"es.wikipedia.org\" domain",
            "match": {
              "location": "file:\\F:\\gitfiles\\githowto\\homework20-KyryloAleksandrov\\src\\steps\\wikipedia-language.steps.ts:21"
            },
            "result": {
              "status": "passed",
              "duration": 92224399
            }
          },
          {
            "arguments": [],
            "keyword": "And ",
            "line": 8,
            "name": "the article title should be visible",
            "match": {
              "location": "file:\\F:\\gitfiles\\githowto\\homework20-KyryloAleksandrov\\src\\steps\\wikipedia-language.steps.ts:26"
            },
            "result": {
              "status": "passed",
              "duration": 70730400
            }
          },
          {
            "keyword": "After",
            "hidden": true,
            "result": {
              "status": "passed",
              "duration": 98556099
            }
          },
          {
            "keyword": "After",
            "hidden": true,
            "result": {
              "status": "passed",
              "duration": 58177400
            }
          }
        ],
        "tags": [],
        "type": "scenario"
      },
      {
        "description": "",
        "id": "wikipedia-article-language-switch;switch-article-to-another-language",
        "keyword": "Scenario Outline",
        "line": 13,
        "name": "Switch article to another language",
        "steps": [
          {
            "keyword": "Before",
            "hidden": true,
            "result": {
              "status": "passed",
              "duration": 8623700
            }
          },
          {
            "keyword": "Before",
            "hidden": true,
            "result": {
              "status": "passed",
              "duration": 134825799
            }
          },
          {
            "arguments": [],
            "keyword": "Given ",
            "line": 4,
            "name": "I am on the Wikipedia homepage",
            "match": {
              "location": "file:\\F:\\gitfiles\\githowto\\homework20-KyryloAleksandrov\\src\\steps\\common.steps.ts:11"
            },
            "result": {
              "status": "passed",
              "duration": 414981400
            }
          },
          {
            "arguments": [],
            "keyword": "When ",
            "line": 5,
            "name": "I search for \"Alan Turing\"",
            "match": {
              "location": "file:\\F:\\gitfiles\\githowto\\homework20-KyryloAleksandrov\\src\\steps\\wikipedia-article.steps.ts:12"
            },
            "result": {
              "status": "passed",
              "duration": 605304399
            }
          },
          {
            "arguments": [],
            "keyword": "And ",
            "line": 6,
            "name": "I switch the article language to \"fr\"",
            "match": {
              "location": "file:\\F:\\gitfiles\\githowto\\homework20-KyryloAleksandrov\\src\\steps\\wikipedia-language.steps.ts:12"
            },
            "result": {
              "status": "passed",
              "duration": 700262099
            }
          },
          {
            "arguments": [],
            "keyword": "Then ",
            "line": 7,
            "name": "I should be on the \"fr.wikipedia.org\" domain",
            "match": {
              "location": "file:\\F:\\gitfiles\\githowto\\homework20-KyryloAleksandrov\\src\\steps\\wikipedia-language.steps.ts:21"
            },
            "result": {
              "status": "passed",
              "duration": 86486600
            }
          },
          {
            "arguments": [],
            "keyword": "And ",
            "line": 8,
            "name": "the article title should be visible",
            "match": {
              "location": "file:\\F:\\gitfiles\\githowto\\homework20-KyryloAleksandrov\\src\\steps\\wikipedia-language.steps.ts:26"
            },
            "result": {
              "status": "passed",
              "duration": 80905999
            }
          },
          {
            "keyword": "After",
            "hidden": true,
            "result": {
              "status": "passed",
              "duration": 133963599
            }
          },
          {
            "keyword": "After",
            "hidden": true,
            "result": {
              "status": "passed",
              "duration": 57972099
            }
          }
        ],
        "tags": [],
        "type": "scenario"
      },
      {
        "description": "",
        "id": "wikipedia-article-language-switch;switch-article-to-another-language",
        "keyword": "Scenario Outline",
        "line": 14,
        "name": "Switch article to another language",
        "steps": [
          {
            "keyword": "Before",
            "hidden": true,
            "result": {
              "status": "passed",
              "duration": 6962700
            }
          },
          {
            "keyword": "Before",
            "hidden": true,
            "result": {
              "status": "passed",
              "duration": 108906699
            }
          },
          {
            "arguments": [],
            "keyword": "Given ",
            "line": 4,
            "name": "I am on the Wikipedia homepage",
            "match": {
              "location": "file:\\F:\\gitfiles\\githowto\\homework20-KyryloAleksandrov\\src\\steps\\common.steps.ts:11"
            },
            "result": {
              "status": "passed",
              "duration": 417331700
            }
          },
          {
            "arguments": [],
            "keyword": "When ",
            "line": 5,
            "name": "I search for \"Alan Turing\"",
            "match": {
              "location": "file:\\F:\\gitfiles\\githowto\\homework20-KyryloAleksandrov\\src\\steps\\wikipedia-article.steps.ts:12"
            },
            "result": {
              "status": "passed",
              "duration": 748425500
            }
          },
          {
            "arguments": [],
            "keyword": "And ",
            "line": 6,
            "name": "I switch the article language to \"de\"",
            "match": {
              "location": "file:\\F:\\gitfiles\\githowto\\homework20-KyryloAleksandrov\\src\\steps\\wikipedia-language.steps.ts:12"
            },
            "result": {
              "status": "passed",
              "duration": 699949800
            }
          },
          {
            "arguments": [],
            "keyword": "Then ",
            "line": 7,
            "name": "I should be on the \"de.wikipedia.org\" domain",
            "match": {
              "location": "file:\\F:\\gitfiles\\githowto\\homework20-KyryloAleksandrov\\src\\steps\\wikipedia-language.steps.ts:21"
            },
            "result": {
              "status": "passed",
              "duration": 79823800
            }
          },
          {
            "arguments": [],
            "keyword": "And ",
            "line": 8,
            "name": "the article title should be visible",
            "match": {
              "location": "file:\\F:\\gitfiles\\githowto\\homework20-KyryloAleksandrov\\src\\steps\\wikipedia-language.steps.ts:26"
            },
            "result": {
              "status": "passed",
              "duration": 150367900
            }
          },
          {
            "keyword": "After",
            "hidden": true,
            "result": {
              "status": "passed",
              "duration": 8321099
            }
          },
          {
            "keyword": "After",
            "hidden": true,
            "result": {
              "status": "passed",
              "duration": 46318100
            }
          }
        ],
        "tags": [],
        "type": "scenario"
      }
    ],
    "id": "wikipedia-article-language-switch",
    "line": 1,
    "keyword": "Feature",
    "name": "Wikipedia article language switch",
    "tags": [],
    "uri": "features\\wikipedia-language.feature"
  },
  {
    "description": "",
    "elements": [
      {
        "description": "",
        "id": "wikipedia-article-references-and-footnotes;jump-to-footnotes-for-a-number-of-references",
        "keyword": "Scenario Outline",
        "line": 10,
        "name": "Jump to footnotes for a number of references",
        "steps": [
          {
            "keyword": "Before",
            "hidden": true,
            "result": {
              "status": "passed",
              "duration": 8536100
            }
          },
          {
            "keyword": "Before",
            "hidden": true,
            "result": {
              "status": "passed",
              "duration": 106745200
            }
          },
          {
            "arguments": [],
            "keyword": "Given ",
            "line": 4,
            "name": "I am on the Wikipedia homepage",
            "match": {
              "location": "file:\\F:\\gitfiles\\githowto\\homework20-KyryloAleksandrov\\src\\steps\\common.steps.ts:11"
            },
            "result": {
              "status": "passed",
              "duration": 424629600
            }
          },
          {
            "arguments": [],
            "keyword": "When ",
            "line": 5,
            "name": "I search for \"Alan Turing\"",
            "match": {
              "location": "file:\\F:\\gitfiles\\githowto\\homework20-KyryloAleksandrov\\src\\steps\\wikipedia-article.steps.ts:12"
            },
            "result": {
              "status": "passed",
              "duration": 578154399
            }
          },
          {
            "arguments": [],
            "keyword": "Then ",
            "line": 6,
            "name": "I should be able to click and view the first 5 valid footnotes",
            "match": {
              "location": "file:\\F:\\gitfiles\\githowto\\homework20-KyryloAleksandrov\\src\\steps\\wikipedia-references.steps.ts:12"
            },
            "result": {
              "status": "passed",
              "duration": 839752599
            }
          },
          {
            "keyword": "After",
            "hidden": true,
            "result": {
              "status": "passed",
              "duration": 8492099
            }
          },
          {
            "keyword": "After",
            "hidden": true,
            "result": {
              "status": "passed",
              "duration": 52365499
            }
          }
        ],
        "tags": [],
        "type": "scenario"
      }
    ],
    "id": "wikipedia-article-references-and-footnotes",
    "line": 1,
    "keyword": "Feature",
    "name": "Wikipedia article references and footnotes",
    "tags": [],
    "uri": "features\\wikipedia-references.feature"
  },
  {
    "description": "",
    "elements": [
      {
        "description": "",
        "id": "wikipedia-homepage-ui;search-input-and-button-are-visible",
        "keyword": "Scenario",
        "line": 3,
        "name": "Search input and button are visible",
        "steps": [
          {
            "keyword": "Before",
            "hidden": true,
            "result": {
              "status": "passed",
              "duration": 8893200
            }
          },
          {
            "keyword": "Before",
            "hidden": true,
            "result": {
              "status": "passed",
              "duration": 107366099
            }
          },
          {
            "arguments": [],
            "keyword": "Given ",
            "line": 4,
            "name": "I am on the Wikipedia homepage",
            "match": {
              "location": "file:\\F:\\gitfiles\\githowto\\homework20-KyryloAleksandrov\\src\\steps\\common.steps.ts:11"
            },
            "result": {
              "status": "passed",
              "duration": 432871699
            }
          },
          {
            "arguments": [],
            "keyword": "Then ",
            "line": 5,
            "name": "the search input should be visible",
            "match": {
              "location": "file:\\F:\\gitfiles\\githowto\\homework20-KyryloAleksandrov\\src\\steps\\wikipedia-home.steps.ts:12"
            },
            "result": {
              "status": "passed",
              "duration": 31300699
            }
          },
          {
            "arguments": [],
            "keyword": "And ",
            "line": 6,
            "name": "the search button should be visible",
            "match": {
              "location": "file:\\F:\\gitfiles\\githowto\\homework20-KyryloAleksandrov\\src\\steps\\wikipedia-home.steps.ts:17"
            },
            "result": {
              "status": "passed",
              "duration": 9873500
            }
          },
          {
            "keyword": "After",
            "hidden": true,
            "result": {
              "status": "passed",
              "duration": 7263399
            }
          },
          {
            "keyword": "After",
            "hidden": true,
            "result": {
              "status": "passed",
              "duration": 94607700
            }
          }
        ],
        "tags": [],
        "type": "scenario"
      }
    ],
    "id": "wikipedia-homepage-ui",
    "line": 1,
    "keyword": "Feature",
    "name": "Wikipedia homepage UI",
    "tags": [],
    "uri": "features\\wikipedia.feature"
  }
]